spotify_album_liker.py
spotify_albumliker-1.0.dist-info/METADATA
spotify_albumliker-1.0.dist-info/RECORD
spotify_albumliker-1.0.dist-info/WHEEL
spotify_albumliker-1.0.dist-info/entry_points.txt
spotify_albumliker-1.0.dist-info/top_level.txt
