Metadata-Version: 2.1
Name: spotify-albumliker
Version: 1.0
Summary: Automatically add songs from your Spotify followed albums into 'all songs'
Home-page: https://github.com/dfresh613/spotify-album-liker
Author: UNKNOWN
Author-email: UNKNOWN
License: UNKNOWN
Platform: UNKNOWN
Requires-Dist: click
Requires-Dist: spotipy
